diin_text/__init__.py
diin_text/_nbdev.py
diin_text/data.py
diin_text/model.py
diin_text-0.0.1.dist-info/LICENSE
diin_text-0.0.1.dist-info/METADATA
diin_text-0.0.1.dist-info/WHEEL
diin_text-0.0.1.dist-info/entry_points.txt
diin_text-0.0.1.dist-info/top_level.txt
diin_text-0.0.1.dist-info/RECORD
