Metadata-Version: 2.1
Name: diin-text
Version: 0.0.1
Summary: Basic math
Home-page: https://github.com/pandya6988/diin_text/tree/master/
Author: pandya6988
Author-email: 1potdish@gmail.com
License: Apache Software License 2.0
Keywords: nbdev
Platform: UNKNOWN
Classifier: Development Status :: 3 - Alpha
Classifier: Intended Audience :: Developers
Classifier: Natural Language :: English
Classifier: Programming Language :: Python :: 3.6
Classifier: Programming Language :: Python :: 3.7
Classifier: Programming Language :: Python :: 3.8
Classifier: License :: OSI Approved :: Apache Software License
Requires-Python: >=3.6
License-File: LICENSE
Requires-Dist: pip
Requires-Dist: packaging
Requires-Dist: numpy
Requires-Dist: argostranslate
Requires-Dist: nbdev
Requires-Dist: bs4
Requires-Dist: matplotlib
Requires-Dist: pandas
Requires-Dist: prettytable
Requires-Dist: seaborn
Requires-Dist: tqdm
Requires-Dist: fastcore
Provides-Extra: dev
